{
  "@type": "Offer",
  "availability": "https://schema.org/InStock",
  "availabilityStarts": "2020-11-21T05:47:14.046Z",
  "createdAt": "2020-11-21T07:58:23.000Z",
  "itemCondition": "https://schema.org/NewCondition",
  "name": "Coles Q10 Power AntiWrinkle Firming Day Cream Face Moisturiser + SPF30",
  "offeredBy": "Coles",
  "price": "11.00",
  "priceCurrency": "AUD",
  "seller": {
    "@type": "Organization",
    "name": "Coles"
  },
  "updatedAt": "2020-11-21T05:47:14.193Z",
  "url": "https://shop.coles.com.au/a/national/product/nivea-q10-plus-day-cream-anti-wrinkle-50ml"
}
