{
  "@type": "Offer",
  "availability": "https://schema.org/InStock",
  "availabilityStarts": "2022-11-29T07:39:11.855Z",
  "createdAt": "2022-11-29T07:39:11.860Z",
  "itemCondition": "https://schema.org/NewCondition",
  "name": "Coles White Christmas Slice",
  "offeredBy": "Coles",
  "price": "7.00",
  "priceCurrency": "AUD",
  "seller": {
    "@type": "Organization",
    "name": "Coles"
  },
  "updatedAt": "2022-11-29T07:39:11.860Z",
  "url": "https://shop.coles.com.au/a/national/product/white-christmas-slice"
}
