{
  "@type": "Product",
  "additionalProperty": [
    {
      "name": "Contains",
      "value": "20g contains 4 baits"
    },
    {
      "name": "Warning",
      "value": "Hazard Classifications 9.1D, 6.3B Read label before use Causes mild skin irritation If skin irritation occurs: Get medical advice/ attention Toxic to aquatic life. This substance must not be applied into or onto water. DO NOT place baits in areas accessible to children or pets. DO NOT spray insecticide on or around the baits as sprays will contaminate baits and reduce effectiveness. DO NOT allow the bait to contact food, food preparation areas or food utensils. DO NOT allow chemical containers or spray to get into drains, sewers, streams or ponds."
    },
    {
      "name": "Size",
      "value": "4 pack"
    },
    {
      "name": "Unit Price",
      "value": "$3.00 per 1Ea"
    }
  ],
  "brand": "Combat",
  "createdAt": "2022-12-05T00:56:33.690Z",
  "description": "Combat Ant Rid Gel Baits",
  "image": "https://shop.coles.com.au/wcsstore/Coles-CAS/images/3/5/8/3582784.jpg",
  "name": "Ant Rid Gel Baits",
  "offers": {
    "@type": "AggregateOffer",
    "highPrice": 12,
    "lowPrice": 12,
    "offerCount": 1,
    "offers": [
      {
        "@context": "http://schema.org",
        "@type": "Offer",
        "availability": "https://schema.org/InStock",
        "availabilityStarts": "2022-12-05T00:56:33.690Z",
        "itemCondition": "https://schema.org/NewCondition",
        "offeredBy": "Coles",
        "price": "12.00",
        "priceCurrency": "AUD",
        "seller": {
          "@type": "Organization",
          "name": "Coles"
        },
        "url": "https://shop.coles.com.au/a/national/product/combat-ant-rid-gel-baits-4x5g"
      }
    ]
  },
  "sameAs": [
    "https://shop.coles.com.au/a/national/product/combat-ant-rid-gel-baits-4x5g"
  ],
  "sku": "3582784",
  "updatedAt": "2022-12-05T00:56:33.690Z"
}
