{
  "@type": "Product",
  "additionalProperty": [
    {
      "name": "Warning",
      "value": "Safety Warnings: Adult supervision required at all time"
    },
    {
      "name": "Unit Price",
      "value": "$6.00 per 1Ea"
    }
  ],
  "brand": "CUB",
  "createdAt": "2022-12-06T02:39:58.281Z",
  "description": "CUB bamboo divided plate. Free from BPA and DEHP. Ideal for plating your CUBs delicious and nutritious meals.",
  "image": "https://shop.coles.com.au/wcsstore/Coles-CAS/images/4/1/4/4146132.jpg",
  "name": "Bamboo Fibre Divided Plate",
  "offers": {
    "@type": "AggregateOffer",
    "highPrice": 6,
    "lowPrice": 6,
    "offerCount": 1,
    "offers": [
      {
        "@context": "http://schema.org",
        "@type": "Offer",
        "availability": "https://schema.org/InStock",
        "availabilityStarts": "2022-12-06T02:39:58.281Z",
        "itemCondition": "https://schema.org/NewCondition",
        "offeredBy": "Coles",
        "price": "6.00",
        "priceCurrency": "AUD",
        "seller": {
          "@type": "Organization",
          "name": "Coles"
        },
        "url": "https://shop.coles.com.au/a/national/product/plate-4146132p-1"
      }
    ]
  },
  "sameAs": [
    "https://shop.coles.com.au/a/national/product/plate-4146132p-1"
  ],
  "sku": "4146132",
  "updatedAt": "2022-12-06T02:39:58.281Z"
}
