{
  "@type": "Product",
  "additionalProperty": [
    {
      "name": "Allergen",
      "value": "Contains Milk"
    },
    {
      "name": "Dietary",
      "value": "No Artificial Flavours or Colours"
    },
    {
      "name": "Warning",
      "value": "BROKEN STICKS RARELY OCCUR BUT MAY CAUSE A CHOKING OR INJURY HAZARD. ADULT SUPERVISION RECOMMENDED FOR CHILDREN 0-5 YEARS."
    },
    {
      "name": "Size",
      "value": "504g"
    },
    {
      "name": "Unit Price",
      "value": "$1.39 per 100G"
    }
  ],
  "brand": "Bulla",
  "createdAt": "2020-11-15T09:55:32.225Z",
  "description": "Bulla Frozen Multi Flavoured Mini Yoghurt Sticks 14 pack",
  "image": {
    "@type": "ImageObject",
    "height": 300,
    "mime": "image/jpeg",
    "url": "https://shop.coles.com.au/wcsstore/Coles-CAS/images/6/0/4/6043866.jpg",
    "width": 300
  },
  "name": "Frozen Multi Flavoured Mini Yoghurt Sticks 14 pack",
  "offers": {
    "@type": "AggregateOffer",
    "highPrice": 7,
    "lowPrice": 7,
    "offerCount": 1,
    "offers": [
      {
        "@context": "http://schema.org",
        "@type": "Offer",
        "availability": "https://schema.org/InStock",
        "availabilityStarts": "2020-11-15T09:55:32.224Z",
        "itemCondition": "https://schema.org/NewCondition",
        "offeredBy": "Coles",
        "price": "7.00",
        "priceCurrency": "AUD",
        "seller": {
          "@type": "Organization",
          "name": "Coles"
        },
        "url": "https://shop.coles.com.au/a/national/product/bulla-fruit-n-yoghurt-frozen-yoghurt-minis-variety-pack"
      }
    ]
  },
  "sameAs": [
    "https://shop.coles.com.au/a/national/product/bulla-fruit-n-yoghurt-frozen-yoghurt-minis-variety-pack"
  ],
  "sku": "6043866",
  "updatedAt": "2020-11-15T09:55:32.224Z"
}
