{
  "@type": "Product",
  "additionalProperty": [
    {
      "name": "Ingredients",
      "value": "Octyl methoxycinnamate 7.5% w/w, Butyl methoxydibenzoylmethane 3% w/w, Diethylamino hydroxybenzoyl hexyl benzoate 2% w/w, Octocrylene 1.9% w/w, Bemotrizinol 0.9% w/w. Also contains: Saccharin and Phenoxyethanol"
    },
    {
      "name": "Contains",
      "value": "Also contains: Saccharin,Thymol and Phenoxyethanol"
    },
    {
      "name": "Warning",
      "value": "Always read the label. Follow the directions for use. Reapply frequently. Avoid prolonged sun exposure and wear protective clothing, hats and eyewear when exposed to the sun."
    },
    {
      "name": "Size",
      "value": "4.25g"
    },
    {
      "name": "Unit Price",
      "value": "$94.12 per 100G"
    }
  ],
  "brand": "Blistex",
  "createdAt": "2022-11-24T08:45:23.000Z",
  "description": "Blistex Lip Balm Conditioning",
  "image": {
    "@type": "ImageObject",
    "height": 300,
    "mime": "image/jpeg",
    "url": "https://shop.coles.com.au/wcsstore/Coles-CAS/images/4/5/1/4510348.jpg",
    "width": 300
  },
  "name": "Lip Balm Conditioning",
  "offers": {
    "@type": "AggregateOffer",
    "highPrice": 4,
    "lowPrice": 4,
    "offerCount": 1,
    "offers": [
      {
        "@context": "http://schema.org",
        "@type": "Offer",
        "availability": "https://schema.org/InStock",
        "availabilityStarts": "2022-11-24T07:44:31.125Z",
        "itemCondition": "https://schema.org/NewCondition",
        "offeredBy": "Coles",
        "price": "4.00",
        "priceCurrency": "AUD",
        "seller": {
          "@type": "Organization",
          "name": "Coles"
        },
        "url": "https://shop.coles.com.au/a/national/product/blistex-lip-balm-conditioning"
      }
    ]
  },
  "sameAs": [
    "https://shop.coles.com.au/a/national/product/blistex-lip-balm-conditioning"
  ],
  "sku": "4510348",
  "updatedAt": "2022-11-24T07:44:31.125Z"
}
