{
  "@type": "Product",
  "additionalProperty": [
    {
      "name": "Ingredients",
      "value": "Infusion Paste: Water, Sugar, Sesame Oil, Honey (6.5%), Golden Syrup (Sugar, Water), Garlic (4.5%), Sea Salt, Corn Starch, Spices (Ginger, Black Pepper, Chilli), Soy Sauce (2.7%) ( Wheat and Soy ), Vinegar, Iodised Salt, Yeast Extract, Burnt Sugar. Finishing Sauce: Water, Sugar, Soy Sauce (12.5%) (Water, Soybeans, Wheat , Salt), Honey (12.5%), Vinegar, Canola Oil, Corn Starch, Sea Salt, Ginger, Iodised Salt, Garlic (0.5%), Burnt Sugar. Contains Soy, Sesame and Wheat. May Contain Celery, Fish, Milk and Mustard."
    },
    {
      "name": "Allergen",
      "value": "Contains Soybean, May Contain Milk, May Contain Fish, Contains Wheat, Contains Sesame Seeds"
    },
    {
      "name": "Servings Per Pack",
      "value": "4.0"
    },
    {
      "name": "Size",
      "value": "150g"
    },
    {
      "name": "Unit Price",
      "value": "$2.00 per 100G"
    }
  ],
  "brand": "Maggi",
  "createdAt": "2022-12-01T04:56:18.698Z",
  "description": "Maggi Stir Fry Creations Honey Soy & Garlic Chicken",
  "image": "https://shop.coles.com.au/wcsstore/Coles-CAS/images/1/1/5/1155170.jpg",
  "name": "Stir Fry Creations Honey Soy & Garlic Chicken",
  "offers": {
    "@type": "AggregateOffer",
    "highPrice": 3,
    "lowPrice": 3,
    "offerCount": 1,
    "offers": [
      {
        "@context": "http://schema.org",
        "@type": "Offer",
        "availability": "https://schema.org/InStock",
        "availabilityStarts": "2022-12-01T04:56:18.696Z",
        "itemCondition": "https://schema.org/NewCondition",
        "offeredBy": "Coles",
        "price": "3.00",
        "priceCurrency": "AUD",
        "seller": {
          "@type": "Organization",
          "name": "Coles"
        },
        "url": "https://shop.coles.com.au/a/national/product/maggi-stirfry-creations-honey-soy-garlic-chicken"
      }
    ]
  },
  "sameAs": [
    "https://shop.coles.com.au/a/national/product/maggi-stirfry-creations-honey-soy-garlic-chicken"
  ],
  "sku": "1155170",
  "updatedAt": "2022-12-01T04:56:18.696Z"
}
