{
  "@type": "Product",
  "additionalProperty": [
    {
      "name": "Ingredients",
      "value": "<p><strong>INGREDIENTS:</strong> <strong>Basa </strong>(99%) [(Pangasius hypophthalmus) Salt, Acidity Regulators (332,330,331,333)]</p>"
    },
    {
      "name": "Allergen",
      "value": "Contains FISH"
    },
    {
      "name": "Servings Per Pack",
      "value": "50.0"
    },
    {
      "name": "Warning",
      "value": "ALL CARE HAS BEEN TAKEN TO REMOVE ALL BONES AND BONE FRAGMENTS, HOWEVER SOME MAY REMAIN.OR HUMAN CONSUMPTION ONLY AND NOT TO BE USED AS BAIT OR FEED FOR AQUATIC ANIMALS"
    },
    {
      "name": "Size",
      "value": "approx. 200g"
    },
    {
      "name": "Unit Price",
      "value": "$9.00 per 1Kg"
    },
    {
      "name": "Country Of Origin",
      "value": "Product of Vietnam"
    }
  ],
  "brand": "Coles Deli",
  "createdAt": "2022-11-29T22:46:26.000Z",
  "description": "Coles Deli Thawed Basa Fillets",
  "image": "https://shop.coles.com.au/wcsstore/Coles-CAS/images/9/3/9/9398755.jpg",
  "name": "Thawed Basa Fillets",
  "offers": {
    "@type": "AggregateOffer",
    "highPrice": 1.8,
    "lowPrice": 1.8,
    "offerCount": 1,
    "offers": [
      {
        "@context": "http://schema.org",
        "@type": "Offer",
        "availability": "https://schema.org/InStock",
        "availabilityStarts": "2022-11-29T19:27:07.659Z",
        "itemCondition": "https://schema.org/NewCondition",
        "offeredBy": "Coles",
        "price": "1.80",
        "priceCurrency": "AUD",
        "seller": {
          "@type": "Organization",
          "name": "Coles"
        },
        "url": "https://shop.coles.com.au/a/national/product/coles-deli-imported-freshwater-basa-fillets-thawed"
      }
    ]
  },
  "sameAs": [
    "https://shop.coles.com.au/a/national/product/coles-deli-imported-freshwater-basa-fillets-thawed"
  ],
  "sku": "9398755",
  "updatedAt": "2022-11-29T19:27:07.659Z"
}
