{
  "@type": "Offer",
  "availability": "http://schema.org/InStock",
  "availabilityStarts": "2022-11-24T12:33:12.799Z",
  "createdAt": "2022-11-24T12:33:20.854Z",
  "itemCondition": "http://schema.org/NewCondition",
  "name": "Woolworths Nescafe Blend 43 Instant Coffee Tin 500G",
  "offeredBy": "Woolworths",
  "potentialAction": {
    "@context": "http://schema.org",
    "@type": "BuyAction"
  },
  "price": 16,
  "priceCurrency": "AUD",
  "seller": {
    "@type": "Organization",
    "name": "Woolworths"
  },
  "updatedAt": "2022-11-24T12:33:20.854Z",
  "url": "https://woolworths.com.au/shop/productdetails/35694/nescafe-blend-43-instant-coffee-tin"
}
