{
  "@type": "Offer",
  "availability": "https://schema.org/InStock",
  "availabilityStarts": "2022-12-06T23:25:45.132Z",
  "createdAt": "2022-12-06T23:25:45.137Z",
  "itemCondition": "https://schema.org/NewCondition",
  "name": "Coles Shapes Multipack Variety 15 Pack",
  "offeredBy": "Coles",
  "price": "5.50",
  "priceCurrency": "AUD",
  "seller": {
    "@type": "Organization",
    "name": "Coles"
  },
  "updatedAt": "2022-12-06T23:25:45.137Z",
  "url": "https://shop.coles.com.au/a/national/product/arnotts-shapes-multipack-variety-15-pack"
}
