{
  "@type": "Offer",
  "availability": "https://schema.org/InStock",
  "availabilityStarts": "2022-11-29T12:12:36.848Z",
  "createdAt": "2020-11-15T04:05:36.000Z",
  "itemCondition": "https://schema.org/NewCondition",
  "name": "Coles Chicken Alfredo Recipe Base",
  "offeredBy": "Coles",
  "price": "2.80",
  "priceCurrency": "AUD",
  "seller": {
    "@type": "Organization",
    "name": "Coles"
  },
  "updatedAt": "2022-11-29T12:12:36.857Z",
  "url": "https://shop.coles.com.au/a/national/product/masterfoods-chicken-alfredo-recipe-base"
}
