{
  "@type": "Recipe",
  "aggregateRating": {
    "@type": "AggregateRating",
    "ratingCount": "1",
    "ratingValue": "5"
  },
  "author": {
    "@type": "Person",
    "name": "Vegan Richa"
  },
  "cookTime": "PT33M",
  "createdAt": "2022-12-05T05:09:09.900Z",
  "datePublished": "2011-04-27T20:11:00+00:00",
  "description": "Aloo methi fried Bondas (Savory potato balls) made into a delicious curry main dish. Vegan and Gluten Free Recipe.&nbsp;",
  "image": [
    "https://www.veganricha.com/wp-content/uploads/2011/04/bonda2.jpg",
    "https://www.veganricha.com/wp-content/uploads/2011/04/bonda2-500x500.jpg",
    "https://www.veganricha.com/wp-content/uploads/2011/04/bonda2-500x375.jpg",
    "https://www.veganricha.com/wp-content/uploads/2011/04/bonda2-480x270.jpg"
  ],
  "keywords": "lentil potato curry, vegan curry recipe",
  "name": "Aloo Methi Bonda Curry (Potato Fenugreek Balls In Gravy)",
  "nutrition": {
    "@type": "NutritionInformation",
    "calories": "209 kcal",
    "carbohydrateContent": "32 g",
    "fatContent": "5 g",
    "fiberContent": "6 g",
    "proteinContent": "7 g",
    "servingSize": "1 serving",
    "sodiumContent": "600 mg",
    "sugarContent": "6 g"
  },
  "prepTime": "PT15M",
  "recipeCategory": "Main Course",
  "recipeCuisine": "Gluten-free",
  "recipeIngredient": [
    "1 boiled medium potato mashed",
    "1/4 cup chopped onions",
    "1 Serrano chili pepper chopped",
    "handful of fresh Methi/Fenugreek leaves chopped (or any greens)",
    "1 teaspoon ginger garlic paste",
    "1/2 teaspoon coriander powder",
    "1/2 teaspoon cumin powder",
    "1/2 teaspoon salt",
    "1/2 teaspoon chili powder (or to taste for spice)",
    "For the batter used for coating",
    "3 tablespoons besan (chickpea/gram flour)",
    "1 garlic clove",
    "2 teaspoons oats",
    "water",
    "1/2 cup onion chopped",
    "2 tomatoes chopped",
    "1 teaspoon garam masala or (1/4 teaspoons each of mustard seeds, coriander powder, cumin powder, 1 bay leaf and a few fennel seeds)",
    "2 teaspoons oil",
    "1/2 teaspoon salt or to taste",
    "1/2 teaspoon sugar",
    "red chili flakes to taste",
    "cilantro for garnish"
  ],
  "recipeInstructions": [
    {
      "@type": "HowToStep",
      "text": "Mash the potatoes and add everything else except ingredients for the batter. Mix well, taste to check for salt and spices, adjust and mix. Make small balls and keep aside."
    },
    {
      "@type": "HowToStep",
      "text": "To make the batter, blend the besan, oats, garlic, salt and some water. Add water a tablespoon at a time to get a thick pasty consistency."
    },
    {
      "@type": "HowToStep",
      "text": "Dip the balls in the batter and deep fry them on medium heat. Serve these balls as snack with cilantro chutney, or tomato ketchup,"
    }
  ],
  "recipeYield": "2",
  "sameAs": [
    "https://veganricha.com/aloo-methi-bonda-curry-potato-fenugreek"
  ],
  "totalTime": "PT48M",
  "updatedAt": "2022-12-05T05:09:09.899Z"
}
