{
  "@type": "Recipe",
  "cookTime": "PT25M",
  "createdAt": "2022-11-22T13:42:21.120Z",
  "datePublished": "2022-06-15",
  "description": "These beef and black bean burritos make for a quick and healthy Mexican inspired dinner.",
  "image": "https://foodhub.scene7.com/is/image/woolworthsltdprod/338579?wid=3631&hei=3631&fmt=png-alpha",
  "keywords": "Beef & Black Bean Burritos",
  "name": "Beef & Black Bean Burritos Recipe | Woolworths",
  "prepTime": "PT15M",
  "recipeCategory": "mains",
  "recipeCuisine": "latin-american",
  "recipeId": "RGWW338579",
  "recipeIngredient": [
    "1 tbs olive oil",
    "500 g beef mince",
    "1 large onion",
    "2 large capsicums",
    "2 cloves garlic",
    "1 tbs smoked paprika",
    "1 tsp cumin",
    "0.5 tsp ground coriander",
    "0.5 cube beef stock",
    "400 g black beans",
    "400 g chopped tomatoes",
    "1 medium lime",
    "500 g wholegrain rice",
    "8 wholewheat tortillas"
  ],
  "recipeInstructions": [
    {
      "@type": "HowToStep",
      "HowToStep": {},
      "text": "Spoon chilli mix into the middle of each tortilla, add rice and any other toppings you like, fold over each end, roll up and serve."
    },
    {
      "@type": "HowToStep",
      "HowToStep": {},
      "text": "Spoon chilli mix into the middle of each tortilla, add rice and any other toppings you like, fold over each end, roll up and serve."
    },
    {
      "@type": "HowToStep",
      "HowToStep": {},
      "text": "Spoon chilli mix into the middle of each tortilla, add rice and any other toppings you like, fold over each end, roll up and serve."
    },
    {
      "@type": "HowToStep",
      "HowToStep": {},
      "text": "Spoon chilli mix into the middle of each tortilla, add rice and any other toppings you like, fold over each end, roll up and serve."
    }
  ],
  "recipeNameId": "beef-and-black-bean-burritos",
  "recipeYield": "4",
  "sameAs": [
    "https://woolworths.com.au/shop/find-recipes/black-bean-burritos"
  ],
  "totalTime": "PT40M",
  "updatedAt": "2022-11-22T13:42:21.120Z",
  "url": "https://www.woolworths.com.au/shop/recipes/beef-and-black-bean-burritos"
}
