{
  "@type": "Recipe",
  "author": {
    "@type": "Person",
    "name": "Produced for Woolworths"
  },
  "cookTime": "PT15M",
  "createdAt": "2022-11-24T22:03:11.000Z",
  "datePublished": "2022-08-03",
  "description": "A creamy pumpkin based fried snack with a savoury sesame seed coating.",
  "image": {
    "@type": "ImageObject",
    "height": 1300,
    "mime": "image/jpeg",
    "url": "https://foodhub.scene7.com/is/image/woolworthsltdprod/chinese-pumpkin-cake-with-cream-cheese:Square-1300x1300",
    "width": 1300
  },
  "keywords": "Cake,Pumpkin,Rice",
  "name": "Chinese Pumpkin Cake with Cream Cheese Recipe | Woolworths",
  "prepTime": "PT15M",
  "recipeCategory": "Desserts",
  "recipeCuisine": "Chinese",
  "recipeId": "RGWW338273",
  "recipeIngredient": [
    "300g glutinous rice flour",
    "500g pumpkin, flesh only",
    "50g sugar",
    "200g cream cheese",
    "2 tbs sesame oil",
    "100g sesame seeds"
  ],
  "recipeInstructions": [
    {
      "@type": "HowToStep",
      "HowToTip": {},
      "text": "Prepare the pumpkin by removing the seeds and skin and then cut the flesh into small chunks."
    },
    {
      "@type": "HowToStep",
      "HowToTip": {},
      "text": "Heat up a non-stick pan to a medium heat and fry the pumpkin for 10 minutes, turning occasionally."
    },
    {
      "@type": "HowToStep",
      "HowToTip": {},
      "text": "Once cooked, remove from the heat and transfer to a mixing bowl and add the sugar."
    },
    {
      "@type": "HowToStep",
      "HowToTip": {},
      "text": "Mash the pumpkin and sugar together while the pumpkin is warm to melt the sugar and then allow to cool."
    },
    {
      "@type": "HowToStep",
      "HowToTip": {},
      "text": "Add the flour to the bowl and combine fully."
    },
    {
      "@type": "HowToStep",
      "HowToTip": {},
      "text": "Divide the dough into 12 balls and flatten into small patties, place some cream cheese in the centre and fold edges to cover the cheese and then dip into the sesame seeds to lightly coat."
    },
    {
      "@type": "HowToStep",
      "HowToTip": {},
      "text": "Put your pan back onto the heat, add the sesame oil and fry the patties for 10 minutes turning halfway until they are golden brown and ready to serve."
    }
  ],
  "recipeNameId": "chinese-pumpkin-cake-with-cream-cheese",
  "recipeYield": "4",
  "sameAs": [
    "https://woolworths.com.au/shop/recipes/chinese-pumpkin-cake-with-cream-cheese"
  ],
  "totalTime": "PT30M",
  "updatedAt": "2022-11-24T18:10:40.973Z",
  "url": "https://www.woolworths.com.au/shop/recipes/chinese-pumpkin-cake-with-cream-cheese"
}
