{
  "@type": "Recipe",
  "aggregateRating": {
    "@type": "AggregateRating",
    "ratingCount": "15",
    "ratingValue": "5"
  },
  "author": {
    "@type": "Person",
    "name": "Beth - Budget Bytes"
  },
  "cookTime": "PT5M",
  "createdAt": "2022-11-25T13:59:36.000Z",
  "datePublished": "2022-01-03T11:39:07+00:00",
  "description": "You only need 5 simple ingredients and about 10 minutes to make this Coconut Curry Ramen, a vibrant bowl full of bold colors and flavors. ",
  "image": {
    "@type": "ImageObject",
    "height": 900,
    "mime": "image/jpeg",
    "url": "https://www.budgetbytes.com/wp-content/uploads/2021/12/Coconut-Curry-Ramen-yellow.jpg",
    "width": 1200
  },
  "keywords": "instant ramen, Ramen Noodles",
  "name": "Coconut Curry Ramen",
  "nutrition": {
    "@type": "NutritionInformation",
    "calories": "770 kcal",
    "carbohydrateContent": "86 g",
    "fatContent": "43 g",
    "fiberContent": "13 g",
    "proteinContent": "18 g",
    "servingSize": "1 recipe",
    "sodiumContent": "1853 mg"
  },
  "prepTime": "PT5M",
  "recipeCategory": "Dinner",
  "recipeCuisine": "American",
  "recipeIngredient": [
    "1 cup frozen mixed vegetables ($0.47)",
    "1.5 cups water ($0.00)",
    "1 3oz. package instant ramen ($0.25)",
    "1/2 cup full fat coconut milk* ($0.52)",
    "1 tsp curry powder ($0.10)"
  ],
  "recipeInstructions": [
    {
      "@type": "HowToStep",
      "text": "Add the frozen vegetables and water to a small saucepot. Place a lid on the pot, turn the heat on to high, and bring the water up to a boil."
    },
    {
      "@type": "HowToStep",
      "text": "Once boiling, add the ramen noodles (without seasoning). Continue to boil for 2-3 minutes, or until the noodles are soft."
    },
    {
      "@type": "HowToStep",
      "text": "Shake the coconut can well to combine the solid fat and liquid before measuring. Add the coconut milk to the saucepot and stir to combine."
    },
    {
      "@type": "HowToStep",
      "text": "Finally, add the seasoning packet from the instant ramen and the curry powder. Stir to combine. Serve hot."
    }
  ],
  "recipeYield": "1",
  "sameAs": [
    "https://budgetbytes.com/coconut-curry-ramen"
  ],
  "totalTime": "PT10M",
  "updatedAt": "2022-11-25T13:22:44.062Z"
}
