{
  "@type": "Recipe",
  "cookTime": "PT130M",
  "createdAt": "2022-11-24T22:03:11.000Z",
  "datePublished": "2022-06-07",
  "description": "Try our easy to follow Moroccan Style Beef Stew recipe. Absolutely delicious with the best ingredients from Woolworths.",
  "image": {
    "@type": "ImageObject",
    "height": 1300,
    "mime": "image/png",
    "url": "https://foodhub.scene7.com/is/image/woolworthsltdprod/morrocan-style-beef-stew?wid=1300&hei=1300&fmt=png-alpha",
    "width": 1300
  },
  "keywords": "Moroccan Style Beef Stew",
  "name": "Moroccan Style Beef Stew Recipe | Woolworths",
  "prepTime": "PT15M",
  "recipeCategory": "mains",
  "recipeCuisine": "african",
  "recipeId": "SP-00263",
  "recipeIngredient": [
    "800 g beef chuck",
    "2 tbs moroccan seasoning",
    "0.25 cup plain flour",
    "2 tbs olive oil",
    "2 brown onions",
    "0.5 head large cauliflower",
    "1 bunch baby carrots",
    "2 large zucchini",
    "8 pitted dates",
    "8 dried apricots",
    "80 g baby spinach",
    "500 g Couscous",
    "100 g chopped toasted pistachios",
    "4 sprigs coriander",
    "4 tbs natural yoghurt",
    "1 lemon"
  ],
  "recipeInstructions": [
    {
      "@type": "HowToStep",
      "HowToStep": {},
      "text": "Serve beef with cous cous, pistachios, coriander, yoghurt and lemon wedges."
    },
    {
      "@type": "HowToStep",
      "HowToStep": {},
      "text": "Serve beef with cous cous, pistachios, coriander, yoghurt and lemon wedges."
    },
    {
      "@type": "HowToStep",
      "HowToStep": {},
      "text": "Serve beef with cous cous, pistachios, coriander, yoghurt and lemon wedges."
    },
    {
      "@type": "HowToStep",
      "HowToStep": {},
      "text": "Serve beef with cous cous, pistachios, coriander, yoghurt and lemon wedges."
    }
  ],
  "recipeNameId": "morrocan-style-beef-stew",
  "recipeYield": "4",
  "sameAs": [
    "https://woolworths.com.au/shop/find-recipes/beef-dinner-recipes"
  ],
  "totalTime": "PT145M",
  "updatedAt": "2022-11-27T09:05:58.979Z",
  "url": "https://www.woolworths.com.au/shop/recipes/morrocan-style-beef-stew"
}
