{
  "@type": "Recipe",
  "createdAt": "2022-11-22T12:23:57.000Z",
  "datePublished": "2022-06-06",
  "description": "Muscovado sugar is used to sweeten these little meringues and give them a toffee-like flavour. They will be popular with everyone.",
  "image": {
    "@type": "ImageObject",
    "height": 1568,
    "mime": "image/png",
    "url": "https://foodhub.scene7.com/is/image/woolworthsltdprod/canape211musfig_013?wid=1269&hei=1568&fmt=png-alpha",
    "width": 1269
  },
  "keywords": "Muscovado & Fig Mini Meringues",
  "name": "Muscovado & Fig Mini Meringues Recipe | Woolworths",
  "prepTime": "PT5M",
  "recipeCategory": "desserts",
  "recipeCuisine": "european",
  "recipeId": "RGR3856",
  "recipeIngredient": [
    "2 figs",
    "1.2 cup baked muscovado mini meringues",
    ".5 cup crème fraîche",
    "2 tsp cocoa powder",
    "60 g plain chocolate"
  ],
  "recipeInstructions": [
    {
      "@type": "HowToStep",
      "HowToStep": {},
      "text": "Arrange 1 fig silver on top then, using a teaspoon, drizzle with melted chocolate. Serve at room temperature."
    },
    {
      "@type": "HowToStep",
      "HowToStep": {},
      "text": "Arrange 1 fig silver on top then, using a teaspoon, drizzle with melted chocolate. Serve at room temperature."
    },
    {
      "@type": "HowToStep",
      "HowToStep": {},
      "text": "Arrange 1 fig silver on top then, using a teaspoon, drizzle with melted chocolate. Serve at room temperature."
    }
  ],
  "recipeNameId": "muscovado-and-fig-mini-meringues",
  "recipeYield": "20",
  "sameAs": [
    "https://woolworths.com.au/shop/find-recipes/meringues-mini"
  ],
  "totalTime": "PT5M",
  "updatedAt": "2022-11-22T11:51:20.375Z",
  "url": "https://www.woolworths.com.au/shop/recipes/muscovado-and-fig-mini-meringues"
}
