{
  "@type": "Recipe",
  "aggregateRating": {
    "@type": "AggregateRating",
    "ratingCount": "12",
    "ratingValue": "4.75"
  },
  "author": {
    "@type": "Person",
    "name": "Beth - Budget Bytes"
  },
  "createdAt": "2022-11-29T07:30:54.335Z",
  "datePublished": "2020-10-11T12:10:10+00:00",
  "description": "Pumpkin Pie Overnight Oats are a great way to use up leftover pumpkin purée and are a delicious make-ahead breakfast for busy mornings.",
  "image": [
    "https://www.budgetbytes.com/wp-content/uploads/2020/10/Overnight-Pumpkin-Pie-Oats-spoon.jpg",
    "https://www.budgetbytes.com/wp-content/uploads/2020/10/Overnight-Pumpkin-Pie-Oats-spoon-500x500.jpg",
    "https://www.budgetbytes.com/wp-content/uploads/2020/10/Overnight-Pumpkin-Pie-Oats-spoon-500x375.jpg",
    "https://www.budgetbytes.com/wp-content/uploads/2020/10/Overnight-Pumpkin-Pie-Oats-spoon-480x270.jpg"
  ],
  "keywords": "baked oatmeal, Cold Oats, Overnight Oats, pumpkin pie, pumpkin pie spice",
  "name": "Pumpkin Pie Overnight Oats",
  "nutrition": {
    "@type": "NutritionInformation",
    "calories": "293.86 kcal",
    "carbohydrateContent": "42.24 g",
    "fatContent": "11.88 g",
    "fiberContent": "6.38 g",
    "proteinContent": "9.85 g",
    "servingSize": "1 bowl",
    "sodiumContent": "350.34 mg"
  },
  "prepTime": "PT5M",
  "recipeCategory": "Breakfast",
  "recipeCuisine": "American",
  "recipeIngredient": [
    "1/3 cup old-fashioned rolled oats ($0.44)",
    "1/2 tsp pumpkin pie spice ($0.05)",
    "1 Tbsp chopped pecans ($0.13)",
    "1/8 tsp salt ($0.01)",
    "1/4 cup pumpkin purée ($0.12)",
    "1/2 Tbsp brown sugar ($0.02)",
    "1/2 cup milk* ($0.18)"
  ],
  "recipeInstructions": [
    {
      "@type": "HowToStep",
      "text": "Add the rolled oats (uncooked), pumpkin pie spice, salt, and chopped pecans to a jar or other resealable container. Top with the pumpkin purée, brown sugar, and milk. Close the container and refrigerate overnight or up to five days."
    },
    {
      "@type": "HowToStep",
      "text": "Before eating, stir the contents of the jar until evenly combined. Enjoy cold or microwave until warmed through."
    }
  ],
  "recipeYield": "1",
  "sameAs": [
    "https://budgetbytes.com/pumpkin-pie-overnight-oats"
  ],
  "totalTime": "PT485M",
  "updatedAt": "2022-11-29T07:30:54.334Z"
}
