{
  "@type": "Recipe",
  "author": {
    "@type": "Person",
    "name": "Fresh Ideas"
  },
  "cookTime": "PT20M",
  "createdAt": "2022-11-26T22:51:30.000Z",
  "datePublished": "2022-05-29",
  "description": "Using only four ingrenients, you'll want to get stuck into this simple sweet potato salad with pork kebabs recipe.",
  "image": {
    "@type": "ImageObject",
    "height": 1300,
    "mime": "image/jpeg",
    "url": "https://foodhub.scene7.com/is/image/woolworthsltdprod/2010-simple-sweet-potato-salad-with-pork-kebabs:Square-1300x1300",
    "width": 1300
  },
  "keywords": "Skewer & kebab,Sweet potato,Pork,Spring,Quick & easy lunch,Nov 2020,Dinner Made Easy,Avocado",
  "name": "Simple Sweet Potato Salad With Pork Kebabs Recipe | Woolworths",
  "prepTime": "PT5M",
  "recipeCategory": "Mains",
  "recipeCuisine": "Australian",
  "recipeId": "10655",
  "recipeIngredient": [
    "300g BBQ smokey paprika sweet potato wedges with ranch drizzle",
    "600g BBQ pork kebabs with capsicum & onion",
    "1 avocado",
    "180g baby leaf salad with beetroot"
  ],
  "recipeInstructions": [
    {
      "@type": "HowToStep",
      "HowToTip": {},
      "text": "Cook sweet potato according to packet instructions, reserving ranch dressing."
    },
    {
      "@type": "HowToStep",
      "HowToTip": {},
      "text": "Meanwhile, heat a greased barbecue grill or chargrill pan over high heat. Cook kebabs, turning, for 5 minutes or until cooked through."
    },
    {
      "@type": "HowToStep",
      "HowToTip": {},
      "text": "Halve avocado and remove seed. Cut into 2cm pieces."
    },
    {
      "@type": "HowToStep",
      "HowToTip": {},
      "text": "Toss salad leaves, sweet potato and avocado in a bowl. Divide among plates. Top with skewers and drizzle over reserved ranch dressing. Serve."
    }
  ],
  "recipeNameId": "simple-sweet-potato-salad-with-pork-kebabs",
  "recipeYield": "4",
  "sameAs": [
    "https://woolworths.com.au/shop/recipes/simple-sweet-potato-salad-with-pork-kebabs"
  ],
  "totalTime": "PT25M",
  "updatedAt": "2022-11-26T11:21:29.001Z",
  "url": "https://www.woolworths.com.au/shop/recipes/simple-sweet-potato-salad-with-pork-kebabs"
}
