{
  "@type": "Recipe",
  "aggregateRating": {
    "@type": "AggregateRating",
    "ratingCount": "20",
    "ratingValue": "5"
  },
  "author": {
    "@type": "Person",
    "name": "Alissa"
  },
  "cookTime": "PT35M",
  "createdAt": "2022-11-29T03:51:21.480Z",
  "datePublished": "2022-03-28T09:39:14+00:00",
  "description": "These vegan stuffed shells will knock your socks off! Made with rich and creamy cashew-tofu ricotta that&#39;s blended with fresh spinach, stuffed into pasta shells and smothered in a quick garlicky tomato sauce...you&#39;d never guess they were dairy-free!",
  "image": {
    "@type": "ImageObject",
    "height": 1200,
    "mime": "image/jpeg",
    "url": "https://www.connoisseurusveg.com/wp-content/uploads/2022/03/vegan-stuffed-shells-22-sq-1.jpg",
    "width": 1200
  },
  "keywords": "dairy-free pasta, vegan pasta recipe",
  "name": "Vegan Stuffed Shells Florentine",
  "nutrition": {
    "@type": "NutritionInformation",
    "calories": "551 kcal",
    "carbohydrateContent": "61.8 g",
    "fatContent": "25.3 g",
    "fiberContent": "10 g",
    "proteinContent": "25.4 g",
    "saturatedFatContent": "4.8 g",
    "servingSize": "5 shells (1/4 of recipe)",
    "sodiumContent": "1024 mg",
    "sugarContent": "18.2 g"
  },
  "prepTime": "PT20M",
  "recipeCategory": "Entree",
  "recipeCuisine": "Italian",
  "recipeIngredient": [
    "6 ounces dried jumbo pasta shells (about 20 shells)",
    "1 tablespoon olive oil",
    "1/2 large onion, (diced)",
    "3 garlic cloves, (minced)",
    "1 (28 ounce or 794 gram) can crushed tomatoes",
    "1/2 tablespoon organic granulated sugar",
    "1 teaspoon dried oregano",
    "1/2 teaspoon salt, (plus more to taste)",
    "1/4 teaspoon black pepper, (plus more to taste)",
    "1/2 cup fresh basil leaves, (torn and lightly packed)",
    "1/2 cup roughly chopped onion (about 1/2 of a medium onion)",
    "1 cup raw cashews (soaked in water 4-8 hours, rinsed and drained)",
    "1/2 cup unflavored and unsweetened soy or almond milk",
    "2 tablespoons lemon juice",
    "1 (14 ounce or 400 gram) package extra firm tofu, (drained and broken into 5-6 large chunks)",
    "2 cups fresh spinach leaves, (coarsely chopped and lightly packed)"
  ],
  "recipeInstructions": [
    {
      "@type": "HowToStep",
      "text": "Bring a large pot of salted water to a boil. Add the pasta shells and cook them according to the package directions."
    },
    {
      "@type": "HowToStep",
      "text": "Drain the pasta into a colander, then return it to the pot and toss it with a few dashes of olive oil. Set aside."
    }
  ],
  "recipeYield": "4",
  "sameAs": [
    "https://connoisseurusveg.com/vegan-stuffed-shells-florentine"
  ],
  "totalTime": "PT55M",
  "updatedAt": "2022-11-29T03:51:21.478Z"
}
